Metadata-Version: 2.1
Name: technobabble
Version: 1.0.2
Summary: Technobabble will own your soul
Home-page: UNKNOWN
Author: Giorgio Vilardo
License: UNKNOWN
Platform: UNKNOWN
Classifier: Programming Language :: Python :: 3
Classifier: Operating System :: OS Independent
Requires-Python: >=3.6
